temprl/__init__.py
temprl/helpers.py
temprl/reward_machines/__init__.py
temprl/reward_machines/automata.py
temprl/reward_machines/base.py
temprl/step_controllers/__init__.py
temprl/step_controllers/base.py
temprl/step_controllers/stateful.py
temprl/step_controllers/stateless.py
temprl/types.py
temprl/wrapper.py
temprl-0.4.0.dist-info/LICENSE
temprl-0.4.0.dist-info/WHEEL
temprl-0.4.0.dist-info/METADATA
temprl-0.4.0.dist-info/RECORD
