Metadata-Version: 2.1
Name: temprl
Version: 0.4.0
Summary: Framework for Reinforcement Learning with Temporal Goals.
Home-page: https://whitemech.github.io/temprl
License: LGPL-3.0-or-later
Keywords: temprl,reinforcement-learning,temporal-logic
Author: MarcoFavorito
Author-email: marco.favorito@gmail.com
Requires-Python: >=3.8,<4.0
Classifier: Development Status :: 2 - Pre-Alpha
Classifier: Intended Audience :: Developers
Classifier: License :: OSI Approved :: GNU Lesser General Public License v3 or later (LGPLv3+)
Classifier: Natural Language :: English
Classifier: Programming Language :: Python :: 3
Classifier: Programming Language :: Python :: 3.10
Classifier: Programming Language :: Python :: 3.8
Classifier: Programming Language :: Python :: 3.9
Requires-Dist: gym (>=0.17.2)
Requires-Dist: numpy (>=1.22.2,<2.0.0)
Requires-Dist: pythomata (==0.3.2)
Project-URL: Bug Tracker, https://github.com/whitemech/temprl/issues
Project-URL: Documentation, https://whitemech.github.io/temprl
Project-URL: Pull Requests, https://github.com/whitemech/temprl/pulls
Project-URL: Repository, https://github.com/whitemech/temprl.git
